pcobra/__init__.py
pcobra/__main__.py
pcobra/cli.py
pcobra/cobra/__init__.py
pcobra/cobra/usar_loader.py
pcobra/cobra/cli/__init__.py
pcobra/cobra/cli/cli.py
pcobra/cobra/cli/cobrahub_client.py
pcobra/cobra/cli/i18n.py
pcobra/cobra/cli/plugin.py
pcobra/cobra/cli/plugin_interface.py
pcobra/cobra/cli/plugin_loader.py
pcobra/cobra/cli/plugin_registry.py
pcobra/cobra/cli/commands/__init__.py
pcobra/cobra/cli/commands/agix_cmd.py
pcobra/cobra/cli/commands/base.py
pcobra/cobra/cli/commands/bench_cmd.py
pcobra/cobra/cli/commands/bench_transpilers_cmd.py
pcobra/cobra/cli/commands/benchmarks2_cmd.py
pcobra/cobra/cli/commands/benchmarks_cmd.py
pcobra/cobra/cli/commands/benchthreads_cmd.py
pcobra/cobra/cli/commands/cache_cmd.py
pcobra/cobra/cli/commands/compile_cmd.py
pcobra/cobra/cli/commands/container_cmd.py
pcobra/cobra/cli/commands/crear_cmd.py
pcobra/cobra/cli/commands/dependencias_cmd.py
pcobra/cobra/cli/commands/docs_cmd.py
pcobra/cobra/cli/commands/empaquetar_cmd.py
pcobra/cobra/cli/commands/execute_cmd.py
pcobra/cobra/cli/commands/flet_cmd.py
pcobra/cobra/cli/commands/init_cmd.py
pcobra/cobra/cli/commands/interactive_cmd.py
pcobra/cobra/cli/commands/jupyter_cmd.py
pcobra/cobra/cli/commands/modules_cmd.py
pcobra/cobra/cli/commands/package_cmd.py
pcobra/cobra/cli/commands/plugins_cmd.py
pcobra/cobra/cli/commands/profile_cmd.py
pcobra/cobra/cli/commands/qualia_cmd.py
pcobra/cobra/cli/commands/transpilar_inverso_cmd.py
pcobra/cobra/cli/commands/verify_cmd.py
pcobra/cobra/cli/repl/__init__.py
pcobra/cobra/cli/repl/cobra_lexer.py
pcobra/cobra/cli/utils/__init__.py
pcobra/cobra/cli/utils/argument_parser.py
pcobra/cobra/cli/utils/config.py
pcobra/cobra/cli/utils/messages.py
pcobra/cobra/cli/utils/semver.py
pcobra/cobra/cli/utils/validators.py
pcobra/cobra/core/__init__.py
pcobra/cobra/core/ast_nodes.py
pcobra/cobra/core/lark_parser.py
pcobra/cobra/core/lexer.py
pcobra/cobra/core/parser.py
pcobra/cobra/core/utils.py
pcobra/cobra/macro/__init__.py
pcobra-10.0.10.dist-info/licenses/LICENSE
pcobra-10.0.10.dist-info/METADATA
pcobra-10.0.10.dist-info/WHEEL
pcobra-10.0.10.dist-info/entry_points.txt
pcobra-10.0.10.dist-info/top_level.txt
pcobra-10.0.10.dist-info/RECORD
