Metadata-Version: 2.4
Name: pcobra
Version: 10.0.10
Summary: Un lenguaje de programación en español para simulaciones y más.
Author-email: Adolfo González Hernández <adolfogonzal@gmail.com>
License: MIT License
Project-URL: Documentation, https://github.com/Alphonsus411/pCobra#readme
Project-URL: Source, https://github.com/Alphonsus411/pCobra
Keywords: cobra,lenguaje,cli
Classifier: License :: OSI Approved :: MIT License
Classifier: Programming Language :: Python :: 3
Classifier: Programming Language :: Python :: 3.9
Classifier: Programming Language :: Python :: 3.10
Classifier: Programming Language :: Python :: 3.11
Requires-Python: >=3.9
License-File: LICENSE
Requires-Dist: numpy==2.3.2
Requires-Dist: scipy==1.16.1
Requires-Dist: matplotlib==3.10.5
Requires-Dist: pandas==2.3.1
Requires-Dist: agix==1.3.0
Requires-Dist: chardet==5.2.0
Requires-Dist: holobit-sdk==1.0.8; python_version >= "3.10"
Requires-Dist: smooth-criminal==0.4.0
Requires-Dist: tomli==2.2.1
Requires-Dist: PyYAML==6.0.2
Requires-Dist: jsonschema==4.25.1
Requires-Dist: python-dotenv==1.1.1
Requires-Dist: pexpect==4.9.0
Requires-Dist: requests==2.32.5
Requires-Dist: flet==0.28.3
Requires-Dist: packaging==25.0
Requires-Dist: pybind11==3.0.1
Requires-Dist: tree-sitter==0.25.1
Requires-Dist: RestrictedPython==8.0
Requires-Dist: prompt_toolkit==3.0.51
Requires-Dist: Pygments==2.19.2
Requires-Dist: argcomplete==3.6.2
Provides-Extra: ml
Requires-Dist: tensorflow==2.20.0; extra == "ml"
Requires-Dist: DEAP==1.3.1; extra == "ml"
Provides-Extra: big-data
Requires-Dist: dask==0.19.0; extra == "big-data"
Provides-Extra: mutation
Requires-Dist: mutpy==0.6.1; extra == "mutation"
Provides-Extra: notebooks
Requires-Dist: papermill==2.6.0; extra == "notebooks"
Requires-Dist: nbconvert==7.16.6; extra == "notebooks"
Requires-Dist: ipykernel==6.29.5; extra == "notebooks"
Provides-Extra: dev
Requires-Dist: python-dotenv==1.1.1; extra == "dev"
Requires-Dist: python-lsp-server==1.13.0; extra == "dev"
Requires-Dist: hypothesis==6.138.3; extra == "dev"
Requires-Dist: ipykernel==6.29.5; extra == "dev"
Requires-Dist: tree-sitter-languages==1.10.2; extra == "dev"
Requires-Dist: pytest==8.4.1; extra == "dev"
Requires-Dist: pytest-cov==6.2.1; extra == "dev"
Requires-Dist: pytest-timeout==2.4.0; extra == "dev"
Requires-Dist: ruff==0.12.8; extra == "dev"
Requires-Dist: mypy==1.17.1; extra == "dev"
Dynamic: license-file
